kernprof.py
line_profiler/timers.h
line_profiler/python25.pxd
line_profiler/__main__.pyi
line_profiler/explicit_profiler.py
line_profiler/profiler_mixin.pyi
line_profiler/cli_utils.py
line_profiler/Python_wrapper.h
line_profiler/_line_profiler.cpp
line_profiler/CMakeLists.txt
line_profiler/_line_profiler.cpython-311-darwin.so
line_profiler/ipython_extension.pyi
line_profiler/line_profiler_utils.pyi
line_profiler/c_trace_callbacks.c
line_profiler/_diagnostics.py
line_profiler/__init__.py
line_profiler/line_profiler_utils.py
line_profiler/line_profiler.pyi
line_profiler/cli_utils.pyi
line_profiler/line_profiler.py
line_profiler/_logger.py
line_profiler/timers.c
line_profiler/explicit_profiler.pyi
line_profiler/profiler_mixin.py
line_profiler/scoping_policy.pyi
line_profiler/py.typed
line_profiler/_line_profiler.pyx
line_profiler/ipython_extension.py
line_profiler/c_trace_callbacks.h
line_profiler/toml_config.py
line_profiler/__main__.py
line_profiler/toml_config.pyi
line_profiler/scoping_policy.py
line_profiler/autoprofile/eager_preimports.pyi
line_profiler/autoprofile/run_module.pyi
line_profiler/autoprofile/eager_preimports.py
line_profiler/autoprofile/util_static.pyi
line_profiler/autoprofile/run_module.py
line_profiler/autoprofile/line_profiler_utils.pyi
line_profiler/autoprofile/ast_tree_profiler.py
line_profiler/autoprofile/autoprofile.pyi
line_profiler/autoprofile/ast_tree_profiler.pyi
line_profiler/autoprofile/__init__.py
line_profiler/autoprofile/line_profiler_utils.py
line_profiler/autoprofile/util_static.py
line_profiler/autoprofile/ast_profile_transformer.py
line_profiler/autoprofile/ast_profile_transformer.pyi
line_profiler/autoprofile/autoprofile.py
line_profiler/autoprofile/profmod_extractor.py
line_profiler/autoprofile/profmod_extractor.pyi
line_profiler/rc/__init__.py
line_profiler/rc/line_profiler.toml
line_profiler-5.0.0.dist-info/RECORD
line_profiler-5.0.0.dist-info/WHEEL
line_profiler-5.0.0.dist-info/entry_points.txt
line_profiler-5.0.0.dist-info/top_level.txt
line_profiler-5.0.0.dist-info/METADATA
line_profiler-5.0.0.dist-info/licenses/LICENSE_Python.txt
line_profiler-5.0.0.dist-info/licenses/LICENSE.txt
